Metadata-Version: 2.1
Name: py3status-pewpew
Version: 0.2
Summary: py3status module to control i3wm with the PewPew
Home-page: https://github.com/obestwalter/py3status-pewpew
License: UNKNOWN
Platform: UNKNOWN
Classifier: Development Status :: 3 - Alpha
Classifier: Operating System :: POSIX :: Linux
Classifier: License :: OSI Approved :: MIT License
Classifier: Environment :: Console
Classifier: Topic :: Utilities
Classifier: Programming Language :: Python
Classifier: Programming Language :: Python :: 3.6
Classifier: Programming Language :: Python :: 3.7
Provides-Extra: lint
Provides-Extra: test
